{
  "world": [
    6,
    30
  ],
  "map_id": 1302,
  "cells": [
    169,
    267
  ],
  "switch_cells": {
    "north": 37,
    "east": 245,
    "south": 456,
    "west": 247
  },
  "obstacles": [
    42,
    46,
    49,
    54,
    64,
    71,
    73,
    75,
    79,
    82,
    86,
    97,
    100,
    103,
    115,
    117,
    132,
    149,
    161,
    164,
    179,
    220,
    268,
    269,
    297,
    298,
    312,
    313,
    336,
    365,
    366,
    367,
    381,
    395,
    403,
    404,
    407,
    408,
    409,
    422,
    426,
    473
  ],
  "saved_at": "2026-05-18 08:54:38"
}